{
  "section_number": "247",
  "title": "[Appeal by partner]. \u2014Omitted by the Finance Act, 1992  (18 of 1992) , s. 84 (w.e.f. 1-4-1993)",
  "chapter": "XX",
  "metadata": {
    "chapter_title": "APPEALSAND REVISION",
    "section_full": "Section 247 - [Appeal by partner]. \u2014Omitted by the Finance Act, 1992  (18 of 1992) , s. 84 (w.e.f. 1-4-1993)",
    "subsection_count": 1
  },
  "chunks": [
    "(1) Every appeal under this Chapter shall be in the prescribed \nform  and shall be verified in the prescribed manner 4[and shall, in case of an appeal made to the \nCommissioner (Appeals) on or after the 1st day of October, 1998, irrespective of the date of initiation of \nthe assessment proceedings relating thereto be accompanied by a fee of, \u2014 \n(i) where the total income of the assessee as computed by the Assessing Officer in the case to \nwhich the appeal relates is one hundred thousand rupees or less, two hundred fifty rupees;"
  ]
}